Metadata-Version: 2.1
Name: workspace-puller
Version: 0.0.22
Summary: Workspace build tool.
Home-page: https://github.com/VasiliyLysokobylko/workspace-puller
Author: onpositive
Author-email: vasily@onpositive.com
License: UNKNOWN
Keywords: workspace,pull,puller
Platform: UNKNOWN
Classifier: Programming Language :: Python :: 3
Classifier: License :: OSI Approved :: MIT License
Classifier: Operating System :: OS Independent
